{"cameraMode":{"drawMode":0,"name":"Shaded","section":"Shading Mode"},"sceneLighting":true,"audioPlay":false,"sceneViewState":{"showFog":true,"showMaterialUpdate":false,"showSkybox":true,"showFlares":true,"showImageEffects":true,"showParticleSystems":true},"in2DMode":false,"pivot":{"x":4.901219844818115,"y":-1.8974699974060059,"z":6.0551838874816898},"rotation":{"x":0.16609345376491548,"y":-0.7610732316970825,"z":0.21464036405086518,"w":0.5893809795379639},"size":2.066025495529175,"orthographic":false}